fpipeline/__init__.py
fpipeline/_version.py
fpipeline/fpipeline.py
fpipeline/requirements.txt
fpipeline-1.3.1.dist-info/LICENSE
fpipeline-1.3.1.dist-info/WHEEL
fpipeline-1.3.1.dist-info/METADATA
fpipeline-1.3.1.dist-info/RECORD
