Metadata-Version: 2.1
Name: fpipeline
Version: 1.3.1
Summary: Functional Pipeline. A simple yet flexible pipeline package based on function composition.
Author-email: BobKerns <rwk@acm.org>
Requires-Python: >=3.12
Classifier: Programming Language :: Python :: 3
Classifier: License :: OSI Approved :: MIT License
Classifier: Operating System :: OS Independent
Project-URL: Bug Tracker, https://github.com/bobkerns/fpipeline/issues
Project-URL: Homepage, https://github.com/bobkerns/fpipeline
